ptudes/__init__.py
ptudes/bag.py
ptudes/data.py
ptudes/fly.py
ptudes/imu_test.py
ptudes/kiss.py
ptudes/utils.py
ptudes/viz_utils.py
ptudes/cli/__init__.py
ptudes/cli/ekf_bench.py
ptudes/cli/flyby.py
ptudes/cli/run.py
ptudes/cli/stat.py
ptudes/cli/viz.py
ptudes/ins/data.py
ptudes/ins/es_ekf.py
ptudes/ins/viz_utils.py
ptudes_lab-0.0.7.dist-info/LICENSE
ptudes_lab-0.0.7.dist-info/METADATA
ptudes_lab-0.0.7.dist-info/WHEEL
ptudes_lab-0.0.7.dist-info/entry_points.txt
ptudes_lab-0.0.7.dist-info/top_level.txt
ptudes_lab-0.0.7.dist-info/RECORD
