Metadata-Version: 2.1
Name: ptudes-lab
Version: 0.0.7
Summary: Ptudes lab: odometry, SLAM and visualization experiments
Home-page: https://github.com/bexcite/ptudes-lab
Author: Pavlo Bashmakov
Author-email: 157482+bexcite@users.noreply.github.com
License: MIT
Project-URL: ptudes Documentation, https://github.com/bexcite/ptudes-lab
Project-URL: Bug Tracker, https://github.com/bexcite/ptudes-lab/issues
Classifier: Development Status :: 3 - Alpha
Classifier: Intended Audience :: Developers
Classifier: Intended Audience :: Education
Classifier: Intended Audience :: Science/Research
Classifier: Operating System :: MacOS
Classifier: Operating System :: Microsoft :: Windows
Classifier: Operating System :: POSIX
Classifier: Operating System :: Unix
Classifier: Programming Language :: Python
Classifier: Programming Language :: Python :: 3
Classifier: Programming Language :: Python :: 3 :: Only
Classifier: Programming Language :: Python :: 3.8
Classifier: Programming Language :: Python :: 3.9
Classifier: Programming Language :: Python :: 3.10
Classifier: Programming Language :: Python :: 3.11
Classifier: Topic :: Software Development :: Libraries
Classifier: Topic :: Scientific/Engineering
Classifier: Topic :: Scientific/Engineering :: Image Processing
Requires-Python: >=3.8, <3.12
License-File: LICENSE
Requires-Dist: numpy>=1.20
Requires-Dist: ouster-sdk>=0.13.0
Requires-Dist: rosbags>=0.9.16
Requires-Dist: matplotlib>=3.5.3
Requires-Dist: kiss-icp<3,>=1.0.0
